leeco/__init__.py
leeco/__init__.pyi
leeco/_annotation_utils.py
leeco/_representations.py
leeco/_timeit_utils.py
leeco/_visualizer.py
leeco/data_structures.py
leeco/py.typed
leeco/structs.py
LeeCo-0.0.1a1.dist-info/METADATA
LeeCo-0.0.1a1.dist-info/WHEEL
LeeCo-0.0.1a1.dist-info/top_level.txt
LeeCo-0.0.1a1.dist-info/RECORD
