Metadata-Version: 2.1
Name: LeeCo
Version: 0.0.1a1
Summary: LeeCo: A utility for empowering the local debugging of LeetCode problems with testcases.
Home-page: https://github.com/JezaChen/LeeCo
Author: Jianzhang Chen
Author-email: jezachen@163.com
License: MIT
Keywords: leetcode
Classifier: Development Status :: 3 - Alpha
Classifier: Intended Audience :: Developers
Classifier: Operating System :: Microsoft :: Windows
Classifier: Programming Language :: Python :: 3.7
Classifier: Programming Language :: Python :: 3.8
Classifier: Programming Language :: Python :: 3.9
Classifier: Programming Language :: Python :: 3.10
Classifier: Programming Language :: Python :: 3.11
Classifier: Programming Language :: Python :: 3.12
Classifier: Development Status :: 4 - Beta
Classifier: License :: OSI Approved :: MIT License
Requires-Python: >=3.7, <4
